.bumpversion.cfg
CONTRIBUTING.md
LICENSE
MANIFEST.in
Makefile
README.md
pyproject.toml
setup.py
CB_IPO/CB_IPO.py
CB_IPO/__init__.py
CB_IPO/__main__.py
CB_IPO/_version.py
CB_IPO.egg-info/PKG-INFO
CB_IPO.egg-info/SOURCES.txt
CB_IPO.egg-info/dependency_links.txt
CB_IPO.egg-info/requires.txt
CB_IPO.egg-info/top_level.txt
CB_IPO/tests/test_all.py
docs/Example Cases.ipynb
docs/Makefile
docs/conf.py
docs/examples.rst
docs/index.rst
docs/installation.rst
docs/make.bat
docs/methods.rst
docs/usage.rst
docs/_build/doctrees/nbsphinx/Example Cases.ipynb
docs/_build/html/Example Cases.ipynb