Metadata-Version: 2.1
Name: CB-IPO
Version: 0.2.0
Summary: Crunchbase and SEC filing scraper
Author-email: Leon <wu.leon@columbia.edu>
License:                                  Apache License
Project-URL: repository, https://github.com/llw2128/CB_IPO
Classifier: Development Status :: 2 - Pre-Alpha
Classifier: Programming Language :: Python :: Implementation :: CPython
Classifier: Programming Language :: Python :: Implementation :: PyPy
Classifier: Programming Language :: Python :: 3
Classifier: Programming Language :: Python :: 3.7
Classifier: Programming Language :: Python :: 3.8
Classifier: Programming Language :: Python :: 3.9
Classifier: Programming Language :: Python :: 3.10
Classifier: Programming Language :: Python :: 3.11
Requires-Python: >=3.7
Provides-Extra: develop
License-File: LICENSE
